awg_scpi/__init__.py
awg_scpi/awg.py
awg_scpi/scpi.py
awg_scpi/siglent.py
awg_scpi-0.2.2.dist-info/LICENSE
awg_scpi-0.2.2.dist-info/METADATA
awg_scpi-0.2.2.dist-info/WHEEL
awg_scpi-0.2.2.dist-info/top_level.txt
awg_scpi-0.2.2.dist-info/RECORD
