Metadata-Version: 2.1
Name: awg-scpi
Version: 0.2.2
Summary: Control of Arbitrary Waveform Generators (AWG) with SCPI command sets like Siglent SDG6022X through python via PyVisa
Home-page: https://github.com/sgoadhouse/awg_scpi
Author: Stephen Goadhouse
Author-email: sgoadhouse@virginia.edu
Maintainer: Stephen Goadhouse
Maintainer-email: sgoadhouse@virginia.edu
License: MIT
Keywords: Siglent,SDG6022X,PyVISA,VISA,SCPI,INSTRUMENT
Platform: UNKNOWN
Classifier: Development Status :: 4 - Beta
Classifier: Intended Audience :: Developers
Classifier: Intended Audience :: Education
Classifier: Intended Audience :: Science/Research
Classifier: License :: OSI Approved :: MIT License
Classifier: Programming Language :: Python
Classifier: Topic :: Scientific/Engineering
Classifier: Topic :: Scientific/Engineering :: Physics
Classifier: Topic :: Software Development
Classifier: Topic :: Software Development :: Libraries
Classifier: Topic :: Software Development :: Libraries :: Python Modules
Requires-Python: >=3.6
License-File: LICENSE
Requires-Dist: pyvisa (>=1.11.3)
Requires-Dist: pyvisa-py (>=0.5.2)
Requires-Dist: argparse
Requires-Dist: QuantiPhy (>=2.3.0)
